[
 {
  "date": "2026-03-13",
  "median": 1999.99,
  "mean": 1972.28,
  "min": 1839.99,
  "max": 2091.43,
  "q1": 1889.99,
  "q3": 2091.43,
  "count": 6,
  "count_filtered": 5
 },
 {
  "date": "2026-03-14",
  "median": 1999.99,
  "mean": 1994.08,
  "min": 1888.99,
  "max": 2091.43,
  "q1": 1949.99,
  "q3": 2091.43,
  "count": 6,
  "count_filtered": 5
 },
 {
  "date": "2026-03-15",
  "median": 1974.99,
  "mean": 1985.06,
  "min": 1888.99,
  "max": 2091.43,
  "q1": 1939.99,
  "q3": 2091.43,
  "count": 7,
  "count_filtered": 6
 },
 {
  "date": "2026-03-16",
  "median": 1999.99,
  "mean": 1994.08,
  "min": 1888.99,
  "max": 2091.43,
  "q1": 1949.99,
  "q3": 2091.43,
  "count": 6,
  "count_filtered": 5
 },
 {
  "date": "2026-03-17",
  "median": 1974.99,
  "mean": 1985.06,
  "min": 1888.99,
  "max": 2091.43,
  "q1": 1939.99,
  "q3": 2091.43,
  "count": 7,
  "count_filtered": 6
 },
 {
  "date": "2026-03-18",
  "median": 1974.99,
  "mean": 1985.06,
  "min": 1888.99,
  "max": 2091.43,
  "q1": 1939.99,
  "q3": 2091.43,
  "count": 7,
  "count_filtered": 6
 },
 {
  "date": "2026-03-19",
  "median": 1974.99,
  "mean": 1985.06,
  "min": 1888.99,
  "max": 2091.43,
  "q1": 1939.99,
  "q3": 2091.43,
  "count": 7,
  "count_filtered": 6
 },
 {
  "date": "2026-03-20",
  "median": 1999.99,
  "mean": 1994.08,
  "min": 1888.99,
  "max": 2091.43,
  "q1": 1949.99,
  "q3": 2091.43,
  "count": 6,
  "count_filtered": 5
 },
 {
  "date": "2026-03-21",
  "median": 1974.99,
  "mean": 1985.06,
  "min": 1888.99,
  "max": 2091.43,
  "q1": 1939.99,
  "q3": 2091.43,
  "count": 7,
  "count_filtered": 6
 },
 {
  "date": "2026-03-22",
  "median": 1974.99,
  "mean": 1985.06,
  "min": 1888.99,
  "max": 2091.43,
  "q1": 1939.99,
  "q3": 2091.43,
  "count": 7,
  "count_filtered": 6
 },
 {
  "date": "2026-03-23",
  "median": 1999.99,
  "mean": 1994.08,
  "min": 1888.99,
  "max": 2091.43,
  "q1": 1949.99,
  "q3": 2091.43,
  "count": 6,
  "count_filtered": 5
 },
 {
  "date": "2026-03-24",
  "median": 1974.99,
  "mean": 1961.73,
  "min": 1799.99,
  "max": 2091.43,
  "q1": 1888.99,
  "q3": 2091.43,
  "count": 7,
  "count_filtered": 6
 },
 {
  "date": "2026-03-25",
  "median": 1974.99,
  "mean": 1961.73,
  "min": 1799.99,
  "max": 2091.43,
  "q1": 1888.99,
  "q3": 2091.43,
  "count": 7,
  "count_filtered": 6
 },
 {
  "date": "2026-03-26",
  "median": 1974.99,
  "mean": 1961.73,
  "min": 1799.99,
  "max": 2091.43,
  "q1": 1888.99,
  "q3": 2091.43,
  "count": 7,
  "count_filtered": 6
 }
]